lidssdk
