Metadata-Version: 1.0
Name: lidssdk
Version: 0.0.3
Summary: lidi
Home-page: UNKNOWN
Author: liyi
Author-email: lisc1991@163.com
License: MIT Licence
Keywords: pip,lids,liyi
Platform: any
